{
    "id": 6,
    "name": "tzy798798",
    "user_id": "user_386",
    "content": "遇龙河漂流是广西桂林阳朔县的一项热门旅游项目，以下是相关介绍：\n\n基本概况\n\n• 河流概况：遇龙河是漓江在阳朔境内最长的一条支流，全长43.5公里，流域面积158.47平方公里，河水清澈平静，素有“小漓江”之称。\n\n• 漂流特色：全程靠手工撑筏，没有机动船干扰，漂流过程安静闲适，能让游客充分欣赏沿途的山水田园风光。\n漂流路线\n\n• 全程漂流：金龙桥-栖凤山-天作寨-遇龙桥-石龙山庄-八仙岩-双狮角逐-情侣山-归义古城-仙桂桥-旅游停车场-八戒仰月-朝阳码头-水车山庄-五指峰-竹林幽境-月亮山-潘庄-骆驼过江-工农桥，全程约12公里，枯水期漂流时间约5小时，丰水期3-4小时。\n\n• 上半程漂流：金龙桥-栖凤山-天作寨-遇龙桥-石龙山庄-八仙岩-双狮角逐-情侣山-归义古城，时长约2.5小时，途经遇龙桥等景点，可欣赏古朴石桥与山水交融的美景。\n\n• 下半程漂流：朝阳码头-水车山庄-青蛙跃江-五指峰-竹林幽境-月亮山-巨鼠飞天-潘庄-骆驼过江-工农桥，时长约2小时，沿途有五指峰、月亮山等自然景观。\n\n最佳游玩时间\n\n• 春季（3-5月）：春暖花开，万物复苏，河水逐渐丰盈，沿岸植被翠绿，风景如画。\n\n• 夏季（6-8月）：夏季是丰水期，河水充沛，适合体验漂流的乐趣，但天气较炎热，需注意做好防晒措施。\n\n• 秋季（9-11月）：秋高气爽，稻田金黄，能欣赏到美丽的田园风光，此时天气较为凉爽，漂流体验也很舒适。\n\n票价信息\n\n• 上半程金龙桥—旧县：255元/筏。\n\n• 中间段旧县-骥马：160元/筏。\n\n• 下半程朝阳码头—工农桥：255元/筏。\n\n• 往返休闲漂：一般是35元/人。\n\n注意事项\n\n• 安全方面：饮酒者、高血压、心脏病、心脑血管等疾病患者以及残疾人士、孕妇、1.2m以下小孩和60岁以上老人不能乘坐竹筏。漂流时需穿戴好救生衣，中途不能脱下，不要下河游泳。\n\n• 物品携带：贵重物品不要带上竹筏，以免入水，非带不可的要用防水器具装好。\n\n• 天气与防晒：做好防晒工作，携带防晒用品。如遇暴雨等恶劣天气，可能会暂停漂流，出行前可关注天气预报。",
    "time": "2025-02-03",
    "score": 3.2,
    "score_count": 6,
    "visited_time": 342,
    "img_list": [
        "images/6_0.jpg",
        "images/6_1.jpg",
        "images/6_2.jpg"
    ]
}