{
    "id": 6,
    "name": "_CFT0****3787",
    "user_id": "user_2961",
    "content": "#济南方特东方神画#是一个老少皆宜的主题乐园，适合家庭亲子休闲旅游，同时也适合年轻人寻奇探险。下面给大家推荐一下济南方特主题乐园必玩项目，助你嗨玩一整天！\n极地快车：听名字就觉得非常的有意思！是我觉得一定要打卡的过山车了🎢惊险刺激一点都没说错🎢！\n海盗船： 非常好玩哦！我每次都玩不厌！！坐在船头或者船尾的感觉更刺激！\n💥🎠🎠🎠💥\n除经典热门的大型项目外，每个园区各有特色！紫藤花长廊、许愿树等唯美景观打卡地；各地特色美食聚会；方特主题乐园，更多好玩之处，等你来发现！要欢乐，去#方特#\n#疫情结束后最想去哪儿#",
    "time": "2020-04-28",
    "score": 4.2,
    "score_count": 8,
    "visited_time": 276,
    "img_list": [
        "images/6_0.jpg",
        "images/6_1.jpg",
        "images/6_2.jpg",
        "images/6_3.jpg",
        "images/6_4.jpg",
        "images/6_5.jpg",
        "images/6_6.jpg",
        "images/6_7.jpg",
        "images/6_8.jpg"
    ]
}