{
    "id": 0,
    "name": "漱石枕流者",
    "user_id": "user_3145",
    "content": "厦门冬季必去！绝美山海Citywalk路线，人少景美随手出片！\n\n厦门的冬天真的太适合旅游了！这条山海步道林海线的Citywalk路线，绝对是你来厦门必打卡的隐藏宝藏！\n\n✨路线亮点：\n1️⃣ 全程2小时，不爬坡不费腿，轻松好走\n2️⃣ 梅海花台超大粉色花海，随手一拍就是大片\n3️⃣ \"厦门小瑞士\"海景绝美，沿途指示牌清晰\n4️⃣ 盼归塔看海，天泉步道看落日，美到窒息\n\n📍路线攻略：\n1️⃣ 打车到东排山路入口，步行3分钟到梅海花台\n2️⃣ 沿指示牌前往\"烤面筋\"，海景+山景一路相伴\n3️⃣ 盼归塔看海，天泉步道看落日，错过可惜\n4️⃣ 下山可逛太清宫，避开高峰期打车方便\n\n✨小贴士：\n建议下午3点出发，冬天落日时间16:45-17:10\n装备：水、耳机、外套、防晒帽\n\n晚餐推荐曾厝垵的草莓夫妇餐厅\n蟹黄拌面、清蒸龙胆鱼、姜母鸭...\n人均100+吃到撑！",
    "time": "2025-02-27",
    "score": 3.0,
    "score_count": 4,
    "visited_time": 55,
    "img_list": [
        "images/0_0.jpg",
        "images/0_1.jpg",
        "images/0_2.jpg",
        "images/0_3.jpg",
        "images/0_4.jpg",
        "images/0_5.jpg",
        "images/0_6.jpg",
        "images/0_7.jpg",
        "images/0_8.jpg",
        "images/0_9.jpg",
        "images/0_10.jpg",
        "images/0_11.jpg",
        "images/0_12.jpg"
    ]
}