{
    "id": 4,
    "name": "清风明月照我还",
    "user_id": "user_2142",
    "content": "公园很大，有吃有玩有健身步道，有自助扫码双人和四人自行车，还有能坐三口之家的电瓶车。绿树成荫，绿草如茵，可坐可卧，来个野餐搭个帐篷都不错。超大的湖面，能看见中国尊、蓝色港湾，还有个沙滩公园，夏天玩水肯定不错。这里的游乐场很大，有旋转木马、过山车、海盗船等等很多项目，大孩幼童玩都适合，人也不多。南门处有个大广场，名烟花广场，其后是喷泉广场，有很多鸽子可以喂食，喷泉场面宏大。公园景色很美，看见好几对拍婚纱照的。公园现在免费游览。",
    "time": "2023-05-11",
    "score": 3.1,
    "score_count": 5,
    "visited_time": 61,
    "img_list": [
        "images/4_0.jpg",
        "images/4_1.jpg",
        "images/4_2.jpg",
        "images/4_3.jpg",
        "https://dimg04.c-ctrip.com/images/1mh2r12000b73dpue419C_W_640_10000.jpg?proc=autoorient",
        "images/4_5.jpg",
        "images/4_6.jpg",
        "images/4_7.jpg",
        "images/4_8.jpg",
        "images/4_9.jpg",
        "images/4_10.jpg",
        "images/4_11.jpg",
        "images/4_12.jpg",
        "images/4_13.jpg",
        "images/4_14.jpg"
    ]
}