{
    "id": 9,
    "name": "M45****161",
    "user_id": "user_2453",
    "content": "这家店藏在沙坡尾。无意间漂了一眼看见好像是家店，买什么罐蛋，当时真是好奇，这是什么。还非遗美食，看的我怦然心动，进店才发现是手工活，将肉塞进蛋黄里！！太有特色了。上菜的时候像炖罐。很精致，打开盖子，香气扑鼻而来。加了鱿鱼和肉羹。整碗都是料，还可以加面一起吃。因为吃饱了就没有加面。还点了同安芋泥包，我本来以为应该是和南瓜饼一样的东西。结果惊喜慢慢，外面很脆。里面甜甜糯糯很好吃！！",
    "time": "2020-01-23",
    "score": 2.1,
    "score_count": 9,
    "visited_time": 339,
    "img_list": [
        "images/9_0.jpg",
        "images/9_1.jpg",
        "images/9_2.jpg",
        "images/9_3.jpg",
        "images/9_4.jpg",
        "images/9_5.jpg",
        "images/9_6.jpg",
        "images/9_7.jpg"
    ]
}