{
    "id": 0,
    "name": "可爱宝贝苗苗的爸爸",
    "user_id": "user_479",
    "content": "踏入秦岭野生动物园，仿佛进入了一片自然的乐园。这里不仅是动物的家园，更是人与自然和谐共处的缩影。园内环境优美，草木葱茏，动物们在宽敞的栖息地中自由活动，展现着最自然的状态。从威猛的狮子、老虎到灵巧的长颈鹿、斑马，每一种动物都让人感受到生命的活力与多样性。\n\n乘坐观光车穿越猛兽区，近距离观察这些草原之王，既紧张又兴奋；而在步行区，与温顺的羊驼、孔雀互动，又让人倍感亲切。园区的设计充分考虑了动物的福利与游客的体验，既保护了动物，又让游客能够近距离感受自然的魅力。\n\n秦岭野生动物园不仅是一次视觉的享受，更是一次心灵的洗礼。它让我更加意识到保护野生动物、维护生态平衡的重要性。离开时，心中充满了对自然的敬畏与对生命的珍视。",
    "time": "2025-02-20",
    "score": 4.0,
    "score_count": 7,
    "visited_time": 821,
    "img_list": [
        "images/0_0.jpg",
        "images/0_1.jpg",
        "images/0_2.jpg",
        "images/0_3.jpg",
        "images/0_4.jpg",
        "images/0_5.jpg",
        "images/0_6.jpg",
        "images/0_7.jpg",
        "images/0_8.jpg",
        "images/0_9.jpg",
        "images/0_10.jpg",
        "images/0_11.jpg",
        "images/0_12.jpg",
        "images/0_13.jpg",
        "images/0_14.jpg"
    ]
}