{
    "id": 6,
    "name": "M19****579",
    "user_id": "user_1449",
    "content": "我是在携程上订的双人票299，比单人票要便宜，位置也很好找，在一个商场里面，就是十点开门，不要去早了，因为去早了也没有地方坐！里面的蜡像有的很真，比大连那个蜡像馆好多了，里面分为不同场景、主题，就是感觉明星少！还有会动的胡巴机器人，一个动画电影，两个小时足够逛完了！还有工作人员在不同的专区给游客拍照，最后要是要照片的话是收费的，好像是110元两张！里面也有做手模的，挺贵的！",
    "time": "2019-04-25",
    "score": 2.7,
    "score_count": 10,
    "visited_time": 716,
    "img_list": [
        "images/6_0.jpg",
        "images/6_1.jpg",
        "images/6_2.jpg",
        "images/6_3.jpg",
        "images/6_4.jpg",
        "images/6_5.jpg",
        "https://dimg04.c-ctrip.com/images/100f13000000v4j0b20F1_W_640_10000.jpg?proc=autoorient",
        "images/6_7.jpg",
        "images/6_8.jpg"
    ]
}