{
    "id": 1,
    "name": "走遍天下XZ",
    "user_id": "user_3343",
    "content": "很多人都把兰州当作甘青游的一个“摆渡站”，心中装满了山川日月，不把兰州放在眼里。其实，兰州的旅游资源非常丰富，来了几次，也没有逛够，白塔山也是第二次登山游览，还是那么的美！\n白塔山，小范围来讲，就是中山桥北端到白塔寺的这一片，慢慢走的话，一、两个小时就可以逛完。大范围来说，叫做“金城关. 黄河古渡景区”，范围就要大得多，估计一天都不一定能玩得下来。\n从中山桥过来要走两侧的人行天桥，然后经过几道巨大的牌坊就进入景区，有一道水幕墙很有意思，有小孩子的话，一定要从后面走一走。往上就是法雨寺、白塔寺等几座古寺，非常值得一看。\n往下看可以看到中山桥的雄姿和滚滚黄河水，记得多看几眼，一生的记忆。\n我们是走上去，再坐索道下来，绝大多数都是先坐索道上去再走下山，不要问为什么，去看看旅游旺季索道下站排起的巨龙般的长队，就明白了。",
    "time": "2024-09-04",
    "score": 3.7,
    "score_count": 10,
    "visited_time": 380,
    "img_list": [
        "images/1_0.jpg",
        "images/1_1.jpg",
        "images/1_2.jpg",
        "images/1_3.jpg",
        "images/1_4.jpg",
        "images/1_5.jpg",
        "images/1_6.jpg",
        "images/1_7.jpg",
        "images/1_8.jpg",
        "images/1_9.jpg",
        "images/1_10.jpg",
        "images/1_11.jpg",
        "images/1_12.jpg",
        "images/1_13.jpg",
        "images/1_14.jpg"
    ]
}