{
    "counts": 10,
    "reviews": [
        {
            "id": 0,
            "name": "银老先生",
            "user_id": "user_1869",
            "content": "【景色】我们一行三个人是晚上来这里参观，国家体育场又名“鸟巢”，在北京奥林匹克公园中心区南部，为2008年北京奥运会的主体育场，举行了2008年夏季奥运会、残奥会开闭幕式、田径比赛及足球比赛决赛，以及2022年冬季奥运会、冬残奥会开闭幕式。来到这里参观感觉场地比较大，周围开阔，环境很好。\n【趣味】我们还是第一次看到这么大的场馆，建筑面积25.8万平方米，可容纳观众9.1万人观看，就是我们来的时候这里还进不去，只能够在外面参观。体育场的形态如同孕育生命的“巢”和摇篮，寄托着人类对未来的希望，外面看起来确实就像鸟筑的巢一样。\n【性价比】外面参观不需要门票费用。进去参观需要门票。",
            "time": "2025-02-06",
            "score": 2.7,
            "score_count": 10,
            "visited_time": 152,
            "img_list": [
                "images/0_0.jpg",
                "images/0_1.jpg",
                "images/0_2.jpg",
                "images/0_3.jpg",
                "images/0_4.jpg",
                "images/0_5.jpg"
            ]
        },
        {
            "id": 1,
            "name": "嘟嘟嘟的世界",
            "user_id": "user_1900",
            "content": "鸟巢，可以花上1-2小时在里面慢慢看看博物馆里陈列的北京奥运会和北京冬奥会的赛前和赛时物品，了解申办的全过程，重温当年的盛况；还可以互动自制冠军照片，挑挑手办和纪念品；累了在休息区喝喝咖啡歇歇脚。",
            "time": "2025-01-12",
            "score": 3.8,
            "score_count": 8,
            "visited_time": 61,
            "img_list": [
                "images/1_0.jpg",
                "images/1_1.jpg",
                "images/1_2.jpg",
                "images/1_3.jpg",
                "images/1_4.jpg",
                "images/1_5.jpg",
                "images/1_6.jpg",
                "images/1_7.jpg",
                "images/1_8.jpg",
                "images/1_9.jpg",
                "images/1_10.jpg",
                "images/1_11.jpg",
                "images/1_12.jpg",
                "images/1_13.jpg",
                "images/1_14.jpg"
            ]
        },
        {
            "id": 2,
            "name": "关裕年guanyunian",
            "user_id": "user_2030",
            "content": "鸟巢🪺🪺🪺🪺🪺🪺是北京的新景点，自从奥运会开幕式后，鸟巢吸引来自世界各地还有全国各地的游客，这里不仅仅有鸟巢还有水立方以及北顶孃孃庙，特别是它的地理位置位于故宫至八达岭长城的路上，从八达岭长城游览回来的人都要来此游览，成了北京新景点，就顺理成章了哦，目前北京的一个不可或缺的景点数不胜数，这里是一个地方。",
            "time": "2025-03-18",
            "score": 4.8,
            "score_count": 10,
            "visited_time": 116,
            "img_list": [
                "images/2_0.jpg",
                "images/2_1.jpg",
                "images/2_2.jpg",
                "images/2_3.jpg",
                "images/2_4.jpg",
                "images/2_5.jpg",
                "images/2_6.jpg",
                "images/2_7.jpg",
                "images/2_8.jpg",
                "images/2_9.jpg",
                "images/2_10.jpg",
                "images/2_11.jpg",
                "images/2_12.jpg",
                "images/2_13.jpg",
                "images/2_14.jpg"
            ]
        },
        {
            "id": 3,
            "name": "关裕年guanyunian",
            "user_id": "user_2115",
            "content": "鸟巢掉进了花海中，北京的春天花香四溢，到处都是花，海棠，山桃，樱花，杏花，梨花，李子花，山楂，金银花还有数不清的各种各样的花，鸟巢掉进了花海中，美不胜收，吸引来自世界各地来的游客，我们居住在鸟巢附近的居民每天都在花海中游荡，这真的成了常态，有福气了。\n十一月，鸟巢开始拆除安检设备，取消安检，所有铁栏杆也撤除，自行车🚲🚲🚲🚲🚲🚲可以进去，又多了一项运动，人们互相分享，兴高采烈的来到这里，享受生活，鸟巢确实给附近的居民带来了实实在在的利益，这里已经是一个乐园。",
            "time": "2024-12-03",
            "score": 1.4,
            "score_count": 6,
            "visited_time": 706,
            "img_list": [
                "images/3_0.jpg",
                "images/3_1.jpg",
                "images/3_2.jpg",
                "images/3_3.jpg",
                "images/3_4.jpg",
                "images/3_5.jpg",
                "images/3_6.jpg",
                "images/3_7.jpg",
                "images/3_8.jpg",
                "images/3_9.jpg",
                "images/3_10.jpg",
                "images/3_11.jpg",
                "images/3_12.jpg",
                "images/3_13.jpg",
                "images/3_14.jpg"
            ]
        },
        {
            "id": 4,
            "name": "Grace_cyt",
            "user_id": "user_2193",
            "content": "7年前来的时候正好下雨，所以就进入内部，走到顶上去参观，这次来算是拔了这根草。门票从原来的80涨到了100，但还是挺值得上去看一看的。先进入室内参观会议厅和展览厅，然后到2楼看一下能同时容纳10万个人的红色座位席，接着坐电梯到5楼看一下钢结构，再走楼梯到鸟巢顶部。鸟巢顶部分布着很多步行道，可以从顶部俯瞰鸟巢的座位席，也可以走到鸟巢的最顶端，俯瞰整个北京。我们傍晚时分上去，看到了晚霞，再过一会儿天黑下来看到对面的水立方亮起来蓝色的灯，还能看到整个北京的夜景，晚霞和夜景都非常漂亮。鸟巢浏览一下差不多两个半到三个小时。",
            "time": "2024-09-24",
            "score": 3.1,
            "score_count": 4,
            "visited_time": 940,
            "img_list": [
                "images/4_0.jpg",
                "images/4_1.jpg",
                "images/4_2.jpg",
                "images/4_3.jpg",
                "images/4_4.jpg",
                "images/4_5.jpg",
                "images/4_6.jpg",
                "images/4_7.jpg",
                "images/4_8.jpg",
                "images/4_9.jpg",
                "https://dimg04.c-ctrip.com/images/1mh4w12000fq90wrqCE0D_W_640_10000.jpg?proc=autoorient",
                "images/4_11.jpg",
                "images/4_12.jpg",
                "images/4_13.jpg",
                "images/4_14.jpg"
            ]
        },
        {
            "id": 5,
            "name": "关裕年guanyunian",
            "user_id": "user_2342",
            "content": "距离家最近的景点，每天散步必到，北京中轴路的路最平坦的路，走路🚶🚶🚶🚶🚶🚶可以健身，逢年过节北京到处人山人海，可是鸟巢仍有湖滨，野鸭嬉戏，喜鹊喳喳叫，一片和谐的世界。",
            "time": "2024-11-02",
            "score": 2.1,
            "score_count": 5,
            "visited_time": 30,
            "img_list": [
                "images/5_0.jpg",
                "images/5_1.jpg",
                "images/5_2.jpg",
                "images/5_3.jpg",
                "images/5_4.jpg",
                "images/5_5.jpg",
                "images/5_6.jpg",
                "images/5_7.jpg",
                "images/5_8.jpg",
                "images/5_9.jpg",
                "images/5_10.jpg",
                "images/5_11.jpg",
                "images/5_12.jpg",
                "images/5_13.jpg",
                "images/5_14.jpg"
            ]
        },
        {
            "id": 6,
            "name": "任大人来了",
            "user_id": "user_2375",
            "content": "真不知道自己来过800多次北京，居然这才是第一次到鸟巢看看。我也是服了自己了。一直都是在电视里看到鸟巢，真不知道到跟前才知道家伙的，原来这么大啊，简直是一场视觉冲击的盛宴！浩大无比的体育场，占了嫩大片面积，周边连个停车位都没，真是担心比赛时公共交通的压力有多大啊……晚上的鸟巢简直了，灯光作用下美哭！！",
            "time": "2018-06-05",
            "score": 4.6,
            "score_count": 5,
            "visited_time": 520,
            "img_list": [
                "images/6_0.jpg",
                "images/6_1.jpg",
                "images/6_2.jpg",
                "images/6_3.jpg",
                "images/6_4.jpg",
                "images/6_5.jpg"
            ]
        },
        {
            "id": 7,
            "name": "If⁰²⁰⁶",
            "user_id": "user_2402",
            "content": "🏯鸟巢体育馆，体育迷心中的圣地！\n🌟北京鸟巢，不仅是2008年北京奥运会的主体育场，更是中国现代化建筑的杰出代表，也是全球瞩目的建筑奇迹。\n💪站在鸟巢的入口，仿佛能感受到那股从历史深处传来的力量。其设计巧妙地将自然元素融入建筑之中，使整个建筑犹如一个巨大的鸟巢，寓意着生命的孕育与重生。\n🌈走进鸟巢，映入眼帘的是那层层叠叠的观众席，它们仿佛是一片片由观众汇聚而成的海洋。每一场比赛或演出，都能吸引无数观众前来，共同为运动员和表演者加油助威。\n🔥除了作为体育比赛和大型演出的场地，鸟巢还是一座充满活力的文化地标。各种展览、演出和文化活动在这里络绎不绝，为游客们带来了丰富多彩的文化体验。\n📸站在鸟巢的观景台上，可以俯瞰整个北京城的美景。无论是远处的城市天际线，还是近处的绿树繁花，都尽收眼底，让人心旷神怡。\n🎉总之，北京鸟巢体育馆是一座集体育、文化、旅游于一体的综合性建筑。它不仅是中国建筑史上的瑰宝，更是全球游客心中的圣地。快来鸟巢感受它的魅力吧！",
            "time": "2025-03-03",
            "score": 2.3,
            "score_count": 10,
            "visited_time": 446,
            "img_list": [
                "images/7_0.jpg",
                "images/7_1.jpg",
                "images/7_2.jpg"
            ]
        },
        {
            "id": 8,
            "name": "If⁰²⁰⁶",
            "user_id": "user_2412",
            "content": "✨鸟巢，中国的骄傲！✨国家体育场，北京的地标建筑，2008年北京奥运会的主体育场，如今依然是北京的一大旅游胜地。👏\n.\n🔥从远处望去，鸟巢的造型独特，像一个巨大的鸟窝，让人忍不住想要靠近。进入鸟巢，你会被它的宏伟壮观所震撼。💪\n.\n鸟巢内部的空间非常宽敞，可以容纳近10万名观众。无论是观看比赛还是参加其他活动，都能感受到它的独特魅力。🎉\n.\n在鸟巢，你可以回顾2008年奥运会的精彩瞬间，也可以欣赏到现代艺术的独特魅力。此外，鸟巢还有丰富的餐饮和购物设施，满足你的各种需求。🍽️🛍️\n.\n总之，鸟巢是一个值得一游的地方，无论是游客还是本地人，都能在这里找到属于自己的乐趣。下次来北京，别忘了去鸟巢看看哦！🏯",
            "time": "2025-03-02",
            "score": 2.8,
            "score_count": 6,
            "visited_time": 983,
            "img_list": [
                "images/8_0.jpg",
                "images/8_1.jpg",
                "images/8_2.jpg"
            ]
        },
        {
            "id": 9,
            "name": "If⁰²⁰⁶",
            "user_id": "user_2421",
            "content": "鸟巢作为2008年北京奥运会的标志性建筑之一，鸟巢不仅仅是一座体育场，更是现代建筑艺术的杰作，吸引着无数游客前来参观。🌈\n📍鸟巢位于北京北四环，交通便利，乘坐地铁10号线或15号线均可到达。从地铁站出站后，步行不远就能到达鸟巢的入口。🚶‍♂️\n走进鸟巢，首先映入眼帘的是它那巨大的钢结构网架，仿佛一只巨大的鸟笼，静静地矗立在那里。🏗️鸟巢的顶部由24根钢柱支撑，结构独特，线条流畅，充满了现代感。\n走进内部，更是美轮美奂。观众席层层叠叠，仿佛一片巨大的海洋。🏊‍♀️站在看台上，可以俯瞰整个北京城的美景，那种震撼感无法用言语表达。\n除了观赏鸟巢的建筑本身，这里还有丰富的互动体验。你可以参加鸟巢的互动展览，了解鸟巢的历史和未来规划，也可以参加体育体验活动，感受奥运精神。🏃‍♂️\n最后，不得不提的是鸟巢的夜景。夜幕降临，鸟巢的灯光璀璨夺目，仿佛一颗巨大的明珠镶嵌在北京城的心脏。🌆\n总之，鸟巢是一次难忘的旅行，让你在欣赏建筑艺术的同时，也能感受到体育的魅力和北京的现代气息。🌟\n如果你也喜欢探索和体验，那么鸟巢绝对是你不可错过的地方。快来加入我们吧！\n·\n#鸟巢探秘#建筑之美#旅游攻略#鸟巢之旅🌈\n📍鸟巢位于北京北四环，交通便利，乘坐地铁10号线或15号线均可到达。从地铁站出站后，步行不远就能到达鸟巢的入口。🚶‍♂️\n走进鸟巢，首先映入眼帘的是它那巨大的钢结构网架，仿佛一只巨大的鸟笼，静静地矗立在那里。🏗️鸟巢的顶部由24根钢柱支撑，结构独特，线条流畅，充满了现代感。\n走进内部，更是美轮美奂。观众席层层叠叠，仿佛一片巨大的海洋。🏊‍♀️站在看台上，可以俯瞰整个北京城的美景，那种震撼感无法用言语表达。\n除了观赏鸟巢的建筑本身，这里还有丰富的互动体验。你可以参加鸟巢的互动展览，了解鸟巢的历史和未来规划，也可以参加体育体验活动，感受奥运精神。🏃‍♂️\n最后，不得不提的是鸟巢的夜景。夜幕降临，鸟巢的灯光璀璨夺目，仿佛一颗巨大的明珠镶嵌在北京城的心脏。🌆\n总之，鸟巢是一次难忘的旅行，让你在欣赏建筑艺术的同时，也能感受到体育的魅力和北京的现代气息。🌟\n如果你也喜欢探索和体验，那么鸟巢绝对是你不可错过的地方。快来加入我们吧！\n·\n#鸟巢探秘#建筑之美#旅游攻略#鸟巢之旅",
            "time": "2025-03-01",
            "score": 3.3,
            "score_count": 6,
            "visited_time": 928,
            "img_list": [
                "images/9_0.jpg",
                "images/9_1.jpg",
                "images/9_2.jpg"
            ]
        }
    ],
    "spot_id": 216
}