{
    "id": 8,
    "name": "不可触碰撞的鱼",
    "user_id": "user_1309",
    "content": "宽窄巷子位于四川省成都市青羊区长顺街附近，由宽巷子、窄巷子、井巷子平行排列组成，全为青黛砖瓦的仿古四合院落，这里也是成都遗留下来的较成规模的清朝古街道，与大慈寺、文殊院一起并称为成都三大历史文化名城保护街区。康熙五十七年（1718年），在平定了准葛尔之乱后，选留千余兵丁驻守成都，在当年少城基础上修筑了满城。民国初年，当时的城市管理者下文，将“胡同”改为“巷子” 。二十世纪80年代，宽窄巷子列入《成都历史文化名城保护规划》。2003年，宽窄巷子街区正式出现在世人的词典中。宽窄巷子是国家AA级旅游景区，先后获2009年“中国特色商业步行街”、四川省历史文化名街、2011年成都新十景、四川十大最美街道等称号。宽窄巷子是成都休闲都市、市井生活的最佳体现。从清朝满城时期的八旗子弟提笼架鸟、莳花弄草；到民国时期达官贵人觥筹交错、大宴宾朋，再到现如今文人游客一杯清茶、一把竹椅品味生活，宽窄巷子已经成为典型成都生活的写照。",
    "time": "2023-01-15",
    "score": 3.5,
    "score_count": 8,
    "visited_time": 866,
    "img_list": [
        "images/8_0.jpg",
        "images/8_1.jpg",
        "images/8_2.jpg",
        "images/8_3.jpg",
        "images/8_4.jpg",
        "https://dimg04.c-ctrip.com/images/0106w12000ag6xq0eA8FA_W_640_10000.jpg?proc=autoorient",
        "images/8_6.jpg",
        "https://dimg04.c-ctrip.com/images/0102o12000ag6yb71B808_W_640_10000.jpg?proc=autoorient",
        "https://dimg04.c-ctrip.com/images/0103x12000ag6x0mkFDE7_W_640_10000.jpg?proc=autoorient"
    ]
}