{
    "id": 5,
    "name": "e03****72",
    "user_id": "user_947",
    "content": "这里风景如画，适合散步和拍照。园内绿化良好，花草树木、水塘小河以及精致的盆景都为游客提供了一个宁静舒适的游览环境。此外，园内的文创产品也很有意思，从传统书法作品到现代设计的纪念品，各种风格都有，适合带回家纪念‌和送友人。\n\n杜甫草堂不仅以其优美的自然景观和宁静的环境吸引游客，更重要的是其深厚的文化底蕴。作为唐代伟大现实主义诗人杜甫流寓成都时的故居，草堂内保存了许多与杜甫相关的历史遗迹和文献资料，每一处都充满了文化的气息。",
    "time": "2024-10-13",
    "score": 4.7,
    "score_count": 7,
    "visited_time": 826,
    "img_list": [
        "images/5_0.jpg",
        "images/5_1.jpg",
        "images/5_2.jpg",
        "images/5_3.jpg",
        "images/5_4.jpg",
        "images/5_5.jpg",
        "images/5_6.jpg",
        "images/5_7.jpg",
        "images/5_8.jpg",
        "images/5_9.jpg"
    ]
}