{
    "id": 1,
    "name": "M56****437",
    "user_id": "user_1383",
    "content": "恭王府，这座昔日皇家府邸，如今成为游客探秘清代文化的绝佳去处。步入其中，仿佛穿越回那个辉煌的年代。银安殿的庄严、后花园的雅致、大戏楼的独特，每一处都让人流连忘返。特别是福字碑，更是镇府之宝，让人感受到历史的厚重与文化的深邃。",
    "time": "2024-12-04",
    "score": 2.6,
    "score_count": 9,
    "visited_time": 997,
    "img_list": [
        "images/1_0.jpg",
        "images/1_1.jpg",
        "https://dimg04.c-ctrip.com/images/1mh2t12000h19ssxf116B_W_640_10000.jpg?proc=autoorient",
        "https://dimg04.c-ctrip.com/images/1mh1x12000h19tyf7CBCD_W_640_10000.jpg?proc=autoorient",
        "https://dimg04.c-ctrip.com/images/1mh5912000h19u5fi7F76_W_640_10000.jpg?proc=autoorient",
        "https://dimg04.c-ctrip.com/images/1mh6a12000h19qxrrE62B_W_640_10000.jpg?proc=autoorient",
        "https://dimg04.c-ctrip.com/images/1mh6k12000h19cpn371A2_W_640_10000.jpg?proc=autoorient",
        "https://dimg04.c-ctrip.com/images/1mh0b12000h19gt8f1FF5_W_640_10000.jpg?proc=autoorient"
    ]
}