{
    "id": 8,
    "name": "伊來",
    "user_id": "user_1337",
    "content": "中国最震撼的身临其境实景演出，没有之一！\n\n长恨歌讲述的是杨玉环与李隆基缠绵悱恻的爱情故事，两人郎才女貌琴瑟和谐，在这华清宫过着神仙般的日子，后因太过放任藩镇军阀，以至于发生事变，杨贵妃最终香消玉损，一代佳话以悲剧收场，可悲可叹啊…\n\n推荐理由：\n1.场景。全剧规模之宏大，国内所有实景演出无出其右者。背靠骊山语罢清宵半，在当年杨玉环真实生活的地方演绎她的故事，实在难得。\n2.舞美。全剧动用了六名舞者出演杨玉环，每个场景所表达的情绪不同，舞态各异，各自精彩，将每段情节的人物和故事表现得淋漓尽致。\n3.特效。四大当中，特效不算最好，特点是演员众多--老谋子的特点嘛，就擅长驾驭大场面。\n\n交通：\n市区有直通旅行专线，跟团游也不错，可以一路听导游讲解。\n\ntips：\n务必购买中央的位置，座间距太窄，前后排坡度不明显，如果坐在了后面，只能看后脑勺了。",
    "time": "2020-07-14",
    "score": 4.5,
    "score_count": 9,
    "visited_time": 164,
    "img_list": [
        "https://dimg04.c-ctrip.com/images/0101l120004ydzg8d8EAD_W_640_10000.jpg?proc=autoorient",
        "https://dimg04.c-ctrip.com/images/01003120004ydzmiv2360_W_640_10000.jpg?proc=autoorient",
        "images/8_2.jpg",
        "https://dimg04.c-ctrip.com/images/0106v120004ydzzs9F495_W_640_10000.jpg?proc=autoorient",
        "https://dimg04.c-ctrip.com/images/01004120004ye04po90E4_W_640_10000.jpg?proc=autoorient",
        "images/8_5.jpg",
        "https://dimg04.c-ctrip.com/images/0106z120004ye0op2DD39_W_640_10000.jpg?proc=autoorient",
        "https://dimg04.c-ctrip.com/images/01006120004ye0qil8A91_W_640_10000.jpg?proc=autoorient",
        "https://dimg04.c-ctrip.com/images/0101u120004ye0x8e8CEF_W_640_10000.jpg?proc=autoorient",
        "https://dimg04.c-ctrip.com/images/01073120004ye0zs1B640_W_640_10000.jpg?proc=autoorient",
        "https://dimg04.c-ctrip.com/images/0100e120004ye19ys5452_W_640_10000.jpg?proc=autoorient",
        "https://dimg04.c-ctrip.com/images/01021120004ye1ku77339_W_640_10000.jpg?proc=autoorient",
        "https://dimg04.c-ctrip.com/images/0100a120004ye1rk09123_W_640_10000.jpg?proc=autoorient",
        "images/8_13.jpg",
        "images/8_14.jpg"
    ]
}