{
    "id": 6,
    "name": "哈哈哈爱旅行🧳",
    "user_id": "user_3287",
    "content": "【性价比】4A级景区而言，青城山后山算性价比很高的，很划算，周末来个成都周边游很方便，一个半小时就到，很凉快\n【景色】很好，自然风光特别好。打卡了青城山本地人开的民宿，特别推荐一下“青城幽悟原宿”，体验感很好，观景效果很棒！算得上网红民宿了吧。青城山之行的意外之喜。民宿还可以看日出日落，星空，不过我来的时候看到了飞雾，也是很开心了\n【趣味】还行吧，毕竟成年人的休假，就是瘫着就好",
    "time": "2020-06-06",
    "score": 3.6,
    "score_count": 8,
    "visited_time": 427,
    "img_list": [
        "images/6_0.jpg",
        "images/6_1.jpg",
        "images/6_2.jpg",
        "images/6_3.jpg",
        "images/6_4.jpg",
        "images/6_5.jpg",
        "images/6_6.jpg"
    ]
}