{
    "id": 3,
    "name": "Wenhq",
    "user_id": "user_1558",
    "content": "龙脊梯田景区很大，主要由金坑红瑶寨、平安壮寨、龙脊古壮寨等三个村寨组成。从桂林过来导航至景区游客中心即可，自驾的只要买门票80元即可，非自驾的要买景交车票。\n    一般游客去的比较多的是平安壮寨，这个寨子开发比较早，设施比较齐全，离景区大门近一点，但接近村寨的最后几公里盘山路很险，平安壮寨梯田主要有二个观景台：九龙五虎、七星伴月，平安寨停车场有去九龙五虎观景台的电瓶车，单程30元，往返55元，从九龙五虎观景台走平路20分钟可以到七星伴月观景台，可以步行下山去停车场，约30分钟，也可以返回到九龙五虎再坐电瓶车回停车场。\n    自驾的游客大部分去金坑住宿，可以在田头寨、大寨住宿，金坑主要有1号观景台西山韶乐、2号观景台千层梯田、3号观景台金佛顶，田头寨离1号、2号观景台很近，大寨离金佛顶较近，大寨附近的索道停车场有索道上金佛顶，单程60元，往返110元。建议住田头寨，很多民宿可以停车。\n   本人是从桂林自驾出发，中午到游客中心，27公里盘山公路到田头寨住宿，下午游2号1号观景台，第二天开车去索道停车场，索道上下游3号观景台，然后去平安壮寨，坐电瓶车上九龙五虎，走路到七星伴月，然后步行下山到停车场，圆满结束游玩。",
    "time": "2022-09-25",
    "score": 2.8,
    "score_count": 9,
    "visited_time": 513,
    "img_list": [
        "images/3_0.jpg",
        "images/3_1.jpg",
        "images/3_2.jpg",
        "images/3_3.jpg",
        "https://dimg04.c-ctrip.com/images/0101412000a01svisF76A_W_640_10000.jpg?proc=autoorient",
        "https://dimg04.c-ctrip.com/images/0101412000a01sn3l076F_W_640_10000.jpg?proc=autoorient",
        "images/3_6.jpg",
        "images/3_7.jpg",
        "images/3_8.jpg"
    ]
}