{
    "id": 0,
    "name": "M52****3571",
    "user_id": "user_2306",
    "content": "桂林芦笛岩景区是桂林著名的国家4A级旅游景区，被誉为“大自然艺术之宫”，是漓江风景名胜区的核心组成部分。以下是关于芦笛岩景区的详细介绍和旅游信息：\n\n\n景区介绍\n芦笛岩位于桂林市西北的桃花江畔，距市中心仅5公里，是离市区较近的知名溶洞。洞内有大量玲珑剔透的石笋、石乳、石柱、石幔、石花，形成了如地下宫殿般的壮丽景观。这里曾接待过多位国内外首脑及政要，被称为“国宾洞”。\n\n\n主要景点\n\n• 水晶宫：这是芦笛岩最宽阔、最美的部分，位于古地下湖深处，钟乳石四悬，如盏盏宫灯，辉煌高贵。\n\n• 雪人景观：洞内有一处罕见的方解石结晶体，灯光升级后，雪花飘飘，仿佛进入冰雪王国。\n\n• 其他景观：如“圆顶蚊帐”“高峡飞瀑”“盘龙宝塔”“原始森林”等，景景相连，移步换景。\n\n\n旅游信息\n\n• 门票价格：成人票90元，半价票45元（适用于6周岁18周岁学生、全日制大学本科及以下学历学生、65周岁以上老人等）。\n\n• 开放时间：08:00-17:30（7月1日-12月31日）；09:00-17:00（1月1日-6月30日）。\n\n• 交通指南：可乘坐市内3路、213路公交车直达景区。\n\n• 游览时间：洞内游览全程约500米，游玩时间约1-3小时。\n\n• 景区服务：\n\n• 导游服务：洞内有免费中文导游讲解，讲解员会详细介绍各个景点。\n\n• 4D视觉秀：利用洞内穹顶打造“芦笛·洞镜”4D视觉秀，带来奇幻的视听体验。\n\n• 停车场：景区提供停车场，收费标准为10元/小时。\n\n• 注意事项：洞内温度较低（17-19℃），建议携带薄外套；洞内地面湿滑，建议穿着舒适的旅游鞋。\n\n\n周边景点\n芦笛岩景区周边还有芳莲池、观石堂鸡血玉博物馆等景点，距离较近，可一并游览。\n\n\n芦笛岩以其独特的岩溶景观和丰富的文化内涵，成为桂林旅游的热门景点之一，适合各个年龄段的游客前来观赏。",
    "time": "2025-02-01",
    "score": 1.8,
    "score_count": 6,
    "visited_time": 82,
    "img_list": [
        "images/0_0.jpg",
        "images/0_1.jpg",
        "images/0_2.jpg",
        "images/0_3.jpg",
        "images/0_4.jpg",
        "images/0_5.jpg",
        "images/0_6.jpg",
        "images/0_7.jpg",
        "images/0_8.jpg"
    ]
}