{
    "id": 7,
    "name": "M42****9350",
    "user_id": "user_425",
    "content": "感谢惠民旅游政策，也非常感谢携程旅游的预约平台，我们是11号预约的12号的门票，两个大人带两个小孩，8点20在宏图大道高架堵了不到两分钟就顺利到停车场，以为九点开门所以提前到馆，非常惊喜的是考虑到人流和高温八点半就排队进馆，不到五分钟就进园了，很人性化哦，极地海洋馆环境干净动物们看起来状态不错，小朋友最喜欢白鲸馆啦，微笑特别治愈哦～免费的游乐室和阅读室是惊喜，萌宠动物园更是惊艳，哈哈，就是到下午的时候人比较多，工作人员看起来挺辛苦的，小朋友今天还摸了工作人员手里的蛇，真是内容丰富收获满满的一天。",
    "time": "2020-08-13",
    "score": 4.2,
    "score_count": 8,
    "visited_time": 304,
    "img_list": [
        "images/7_0.jpg",
        "images/7_1.jpg",
        "images/7_2.jpg",
        "images/7_3.jpg",
        "images/7_4.jpg",
        "images/7_5.jpg",
        "images/7_6.jpg",
        "images/7_7.jpg",
        "images/7_8.jpg",
        "images/7_9.jpg"
    ]
}