{
    "id": 4,
    "name": "愉行人",
    "user_id": "user_2047",
    "content": "去渝东南自驾游，第一个自然景观游览首选乌江画廊。我们买的万足至龚滩单行票，从彭水万足乌江画廊码头上船，船行2小时右到龚滩古镇，乌江画廊名符其实，景色美不胜收。买票前一定要注意买哪条线路和发船班次。这里没有代驾服务，我们的车只能由一位同行的朋友放弃乘船同行，让他将车开到龚滩古镇后再汇合。当然可以选择购往返票，但就比较耗时了。还有另一个游览选择就是买万足-鹿角-万足的票，线路不一样，时间也要短些，但游完后可以回到万足码头，继续自驾前行。",
    "time": "2021-05-15",
    "score": 1.4,
    "score_count": 7,
    "visited_time": 37,
    "img_list": [
        "images/4_0.jpg",
        "images/4_1.jpg",
        "images/4_2.jpg",
        "images/4_3.jpg",
        "images/4_4.jpg",
        "images/4_5.jpg"
    ]
}