{
    "id": 7,
    "name": "漫悠旅行A",
    "user_id": "user_2182",
    "content": "有句话是这么说的“三亚归来不看海，除却亚龙不是湾”！以前觉得这句话太夸张了，直至我踩在洁白细腻的沙滩上，看着纯净美艳的亚龙湾，这才意识到自己见识太少！\n\n亚龙湾发展历史：\n亚龙湾 古称琊琅湾，琊或琅意为 白玉 ，形容沙子洁白如玉。又因为这里的海湾呈月牙形，所以有人称其为“牙龙湾”……再后来，慢慢演变成 亚龙湾 。 亚龙湾 以野猪岛为中心，东西蔓延长达七八公里。沿着海岸线，这里分布着不少豪华度假酒店。\n\n🌟亮点特色：\n水质干净，清澈见底；水有层次感，从薄荷绿到浅蓝，深蓝等，各种颜色很漂亮！\n\n周边景点推荐：\n热带天堂森林公园，冯小刚电影《非诚勿扰》取景地。\n\n🛒周边购物推荐：\n奥特莱斯。\n\n😋周边美食推荐：\n林姐香味海鲜（📍详细地址：龙溪路6号亚龙湾壹号小镇地下一层GB007室；🕙营业时间：10：00—22：00 ；推荐椒盐皮皮虾、辣炒竹蛏、海胆蒸蛋。）\n\n🚗交通攻略：\n公交28路；如果打车的话，价格在60-70之间！\n\n🕙开放时间：\n全天开放\n\n💰门票价格：\n沙滩免费\n\n📌小Tips：\n1、天黑的时候，沙滩上会有很多小虫子和红蚂蚁，尽量在天黑之前回到酒店！\n\n2、沙滩上有很多海上娱乐项目，参与项目的时候要多问价，多对比，选择靠谱的！毕竟海上项目，也存在一些风险，要尽量把风险降到最低！",
    "time": "2020-05-30",
    "score": 2.4,
    "score_count": 8,
    "visited_time": 334,
    "img_list": [
        "images/7_0.jpg",
        "images/7_1.jpg",
        "images/7_2.jpg",
        "images/7_3.jpg",
        "images/7_4.jpg",
        "images/7_5.jpg",
        "images/7_6.jpg",
        "images/7_7.jpg",
        "images/7_8.jpg",
        "images/7_9.jpg",
        "images/7_10.jpg",
        "images/7_11.jpg",
        "images/7_12.jpg",
        "images/7_13.jpg",
        "images/7_14.jpg"
    ]
}