{
    "id": 0,
    "name": "偶尔装一下",
    "user_id": "user_2602",
    "content": "第三节课，成都博物馆\n从盐市口乘47路公交车西御路下车，过个马路就是，成都博物馆的人气还是很高的，除了知名品牌的餐饮店聚集的长长队伍，优越的地理位置也令他额外醒目。\n以下学当地市民简称，成博。\n预约的时候，午时已过，由于老太太有点疲劳过度，我带着她走马观花的大概转了转。馆很新，没来的及看是什么时候成立的，文物也是来自历朝历代的先贤瑰宝。一楼的展品非常独特，谁看谁高兴，不信，见下图。\n每个不同年龄段的人物，面部表情都像是吃了喜鹊蛋似的，笑的合不拢嘴，看着那叫一个喜庆。成博的文物是老的，但建筑是当代的风格，二楼以上没去，因为看到一楼忙碌的工作人员在布展，真的是来不逢时，墨西哥的美州豹风情展出次日才开始，我和老太太早上从武候祠逛完已经人困马乏，我决定改日再来，老太太身体重要。\n一日后，再来逛，嗨，时运不济，入场票，没约上，悻悻而归。在牡丹广场拍了几张照片，返城就餐。\n成博，我看的不全面，这份自习试卷，自己批阅不及格。因为我将题都没有做完。留点遗憾也是念想，有期待就会有向往，来日方长，故地重游。\n心得体会，将日子过成段子和將生活过成诗，是一样的，只要远方触手可及并不遥远，可望而不可及。生活不能太满，水满则溢，物极必反，月满则亏，欲速则不达，要学会留白。看看这些文物的表情，一幅知足常乐的心态，有没感染到你。",
    "time": "2024-07-01",
    "score": 4.7,
    "score_count": 10,
    "visited_time": 823,
    "img_list": [
        "images/0_0.jpg",
        "images/0_1.jpg",
        "images/0_2.jpg",
        "images/0_3.jpg",
        "images/0_4.jpg",
        "images/0_5.jpg",
        "images/0_6.jpg",
        "images/0_7.jpg",
        "images/0_8.jpg",
        "images/0_9.jpg",
        "images/0_10.jpg",
        "images/0_11.jpg",
        "images/0_12.jpg",
        "images/0_13.jpg",
        "images/0_14.jpg"
    ]
}