{
    "id": 5,
    "name": "M15****821",
    "user_id": "user_917",
    "content": "周日带儿子去了上海自然博物馆，体验超棒！\n \n一进去，就像进入了一个神奇的自然世界。丰富的标本和场景还原，让孩子们可以直观地了解大自然的奥秘。对于亲子游来说，这里简直是宝藏。儿子兴奋地穿梭在各个展厅，一会儿看看巨大的恐龙化石，一会儿又被逼真的动物标本吸引，不停地问问题，好奇心完全被激发出来。\n \n馆内的互动区域也设计得十分精妙，儿子在那里玩得不亦乐乎，通过简单的操作就能学到知识，真正做到了寓教于乐。而且整个博物馆的布局很合理，参观路线流畅，即使人多也不会觉得拥挤杂乱。",
    "time": "2024-11-05",
    "score": 2.6,
    "score_count": 9,
    "visited_time": 950,
    "img_list": [
        "images/5_0.jpg",
        "images/5_1.jpg",
        "images/5_2.jpg",
        "images/5_3.jpg",
        "images/5_4.jpg",
        "images/5_5.jpg",
        "images/5_6.jpg",
        "images/5_7.jpg",
        "images/5_8.jpg"
    ]
}