{
    "name": "南京市博物馆(朝天宫)",
    "id": 221,
    "score": "4.6",
    "type": "赏花胜地",
    "reviews": 10,
    "url": "https://you.ctrip.com/sight/nanjing9/18087.html?scene=online",
    "img": "https://dimg04.c-ctrip.com/images/1lo6j12000der785zF57F_C_220_140.jpg?proc=autoorient",
    "info": [
        {
            "地址": "南京市秦淮区王府大街朝天宫4号"
        },
        {
            "开放时间": "今日已闭园；明日09:00-17:00开放（16:30停止入园）"
        }
    ],
    "introduce": {
        "介绍": "朝天宫是清代的文庙，整个建筑群包括了江宁府学、朝天宫、以及由朝天宫的几间大殿辟成的南京市博物馆。现在江宁府学为江苏省昆剧院，只能外观，游客能入内参观的只有朝天宫和南京市博物馆。朝天宫的历史朝天宫的历史可追溯至春秋，吴王夫差在这里的冶山冶铁铸剑，建文庙的历史可追溯至北宋，明代命名为朝天宫，是皇室礼拜道教诸神和学习朝见天子礼仪的场所，后毁于战火，清同治五年至九年（公元1866年-1870年）在原有基础上改建，又成为了文庙，江宁府学也从鸡鸣山迁于此处。朝天宫朝天宫南临人工运河“运渎”，有“万仞宫墙”围绕，墙内有一泮池，东西两侧分别为“德配天地”和“道贯古今”牌坊。主体建筑从东南到西北依次为棂星门、大成门、大成殿、崇圣殿，顶覆黄色琉璃瓦，棂星门下的四对团龙雕像栩栩如生，大成门前立着孔子塑像。崇圣殿后是后花园部分，东边的飞云阁附近是乾隆御碑亭，西边的敬一亭是冶山最高处。南京市博物馆崇圣殿的一侧是南京市博物馆的主展厅，主要有基本陈列《龙蟠虎踞--南京城市史展》。展品按照时代更迭的顺序排列，一层是远古到明清的展品，二层是民国时期的展品。三层是《玉堂佳器--馆藏精品展》，“镇馆之宝”元末明初的青花梅瓶即在这，瓶上惟妙惟肖地绘着“萧何月下追韩信”图。南京市博物馆将大成殿和崇圣殿辟为特展和临时展展厅，朝天宫正在举办的展览都会写在门口的牌子上。",
        "开放时间": "01/01-01/26 周二-周日 09:00-17:00开放;01/28-12/31 周二-周日 09:00-17:00开放;01/01-01/26 周一 全天不开放;01/28-12/31 周一 全天不开放;春节 09:00-18:30开放;01/27 09:00-17:00开放",
        "优待政策": [
            {
                "未成年": "：18周岁（不含）以下（按生日计算年龄），免费"
            },
            {
                "大学生": "：全日制大学在读学生，半价"
            },
            {
                "老人": "：60周岁（含）-69周岁（含），持老年证或身份证，半价；70周岁(含)以上，持老年证或身份证，免费"
            },
            {
                "离休干部": "：离休干部证，免费"
            },
            {
                "残疾人": "：凭残疾证，免费"
            },
            {
                "军人": "：人民解放军、武警部队现役军人、有军籍的军校学员，凭相关证件，免费"
            },
            {
                "伤残军人": "：凭相关证件，免费"
            },
            {
                "退役军人": "：凭相关证件，免费；凭《中华人民共和国退役军人优待证》，免费"
            },
            {
                "无偿捐献者": "：获得国家无偿献血奉献奖、无偿捐献造血干细胞奖和无偿献血志愿服务终身荣誉奖的个人凭相关证件，免费"
            },
            {
                "南京市医护人员": "：凭南京市域内医疗卫生机构颁发的医务人员有效工作证件和居民身份证入馆，有效期:2023年1月~2025年12月(场馆正常开放时间，活动不包含夜间开放，如遇特殊情况请以场馆公告为准)\n本市医务人员可凭有效直系亲属证明，携带1-2名直系亲属享受免费入馆浏览优待，免费"
            },
            {
                "三属人员": "：凭《中华人民共和国烈士、因公牺牲军人、病故军人遗属优待证》，免费"
            },
            {
                "消防救援人员": "：在职、退休、残疾消防救援人员、消防救援学院学院凭本人有效相关证件，免费"
            }
        ]
    }
}