{
    "id": 1,
    "name": "视觉小鹏",
    "user_id": "user_1918",
    "content": "看不一样的新春灯会，就来泉城欧乐堡梦幻世界赏/观/看/逛/品/玩 过！新！年！\n\n推荐理由:\n☝️震撼大型裸眼3D城堡夜光幻影秀\n✌️新年烟花秀、梦幻花灯海\n☝️数百架无人机超燃星空秀\n✌️数十组大型自贡新春灯组.\n☝️非物质文化遗产——钢花火龙\n✌️新春庙会、超大乐园...\n春节、元宵节、情人节\n美好的节日都在这里！👍\n情人节、元宵节延迟至深夜24点！\n\n⚠️项目时刻:\n1⃣️大型新年烟花秀(每晚20:08在天鹅堡表演，元宵节及情人节加演24点场，烟花秀时长10分钟左右)。没有烟花秀的灯会不是完整的新春灯会!\n \n活动期间，近50种造型的烟花在天空绚丽燃放!\n济南及周边灯会中只有欧乐堡有烟花秀，能在这里看烟花，真的太～太～太完美了，带着你的Ta一起来! \n\n2⃣️无人机星空秀(每晚19:50在天鹅堡上空表演一场，元宵节及情人节加演23:40点场，观赏点为天鹅堡正前方喷泉广场，每场时长10分钟左右)。\n\n3⃣️裸眼3D城堡夜光幻影秀(每晚18、19、20、21、22点分别在天鹅堡城堡上表演一场,元宵节及情人节加演23点、23:50场，每场时长8分钟左右) !\n4⃣️钢花火龙(每晚18:30、20:40分别在云端冲刺项目旁表演一场，元宵节及情人节加演22:30场，观赏点为云端冲刺项目两侧，每场15分钟左右)，超级震撼!\n\n⚠️网红打卡项目(超适合情侣、亲子) :\n1⃣️炫彩极光，光与影的配合极致炫彩。不用去出国，也能看到童话里美丽的极光！\n2⃣️浪漫玫瑰花海&桃花岛：数万株红、 黄玫瑰和桃花树空降！组成大片浪漫的发光玫瑰花海&桃花花海!新春期间和男(女) 票的约会地点就在这里！\n3⃣️Kiss tree：在树下相拥亲吻，背后的树像感应到彼此的真情一样，自动被点亮，无声的表白。\n除此之外，还有各种互动表演，热闹的舞龙舞狮、新春卡通巡游，保证嗨一整天都停不下来！由重点还可以玩乐园——山东超大的游乐园！\n5D影院、过山车、海盗船、旋转木马、儿童乐园等，众多游乐项目让你玩到嗨！",
    "time": "2021-02-10",
    "score": 1.1,
    "score_count": 9,
    "visited_time": 405,
    "img_list": [
        "images/1_0.jpg",
        "images/1_1.jpg",
        "images/1_2.jpg",
        "images/1_3.jpg",
        "images/1_4.jpg",
        "images/1_5.jpg",
        "images/1_6.jpg",
        "images/1_7.jpg",
        "images/1_8.jpg"
    ]
}