{
    "name": "杜甫江阁",
    "id": 74,
    "score": "4.6",
    "type": "历史建筑",
    "reviews": 10,
    "url": "https://you.ctrip.com/sight/changsha148/1415165.html?scene=online",
    "img": "https://dimg04.c-ctrip.com/images/0105h1200087ee8zuF875_C_220_140.jpg?proc=autoorient",
    "info": [
        {
            "地址": "长沙市天心区湘江中路108号"
        },
        {
            "开放时间": "开园中；09:00-22:00开放"
        },
        {
            "官方电话": "0731-82298545(游客中心),0731-89824455(六楼远山会茶室)"
        }
    ],
    "introduce": {
        "介绍": "这是一座临江建筑，是为了纪念唐代大诗人杜甫而建的仿古建筑。因为靠近湘江，非常适合观看橘子洲的焰火表演。如今杜甫江阁是当地的标志性建筑，来这里登高远眺湘江两岸，喝喝茶，吹吹江风，很惬意。杜甫江阁内有大诗人的生平介绍，每当夏季周末放焰火时，前来观看的游人会增加很多，需要提前来才能占据一个好位置。",
        "开放时间": "01/01-01/30 09:00-22:00开放;02/05-12/31 09:00-22:00开放;01/31-02/04 11:00-21:30开放",
        "优待政策": [
            {
                "儿童": "：14周岁(不含)以下，免费"
            },
            {
                "老人": "：65周岁(含)以上，免费；60周岁(含)-65周岁(不含)之间，半价"
            },
            {
                "军人": "：现役军人、现役军人家属、“三属”(烈士、因公牺牲军人、病故军人的遗属)、残疾军人、退役军人、军队离退休干部凭有效证件，免费"
            },
            {
                "未成人": "：14周岁(含)-18周岁(不含)之间，半价"
            },
            {
                "学生": "：全日制大学本科及以下学历在校学生凭有效证件，半价"
            },
            {
                "残疾人": "：凭有效证件，免费"
            },
            {
                "补充说明": "：法律、法规对免票价格优惠政策另有规定的从其规定。以上信息仅供参考，具体详情请以景区当天披露为准。"
            }
        ]
    }
}