{
    "id": 7,
    "name": "陪伴成长2019",
    "user_id": "user_1553",
    "content": "栖霞山还是很大的，如果能免费就好了，十一去的枫叶还没红很可惜，山里蝴蝶很多，春蹦蹦，小昆虫很多，孩子还抓到了一只土灰色的螳螂。有一片有很多小红果树，虽然不能吃，不过孩子摘了一些体验了一把采摘乐趣。\n桃花涧可以踩石头过小溪，主要是爬山，中间一些小插曲也很有意思",
    "time": "2020-10-15",
    "score": 3.6,
    "score_count": 7,
    "visited_time": 692,
    "img_list": [
        "images/7_0.jpg",
        "images/7_1.jpg",
        "https://dimg04.c-ctrip.com/images/010731200086qap0hE8BB_W_640_10000.jpg?proc=autoorient",
        "images/7_3.jpg",
        "images/7_4.jpg",
        "https://dimg04.c-ctrip.com/images/010191200086q9op0EE6B_W_640_10000.jpg?proc=autoorient",
        "images/7_6.jpg",
        "https://dimg04.c-ctrip.com/images/0103c1200086qa1luAE7F_W_640_10000.jpg?proc=autoorient",
        "https://dimg04.c-ctrip.com/images/010171200086q9pvfBD47_W_640_10000.jpg?proc=autoorient",
        "https://dimg04.c-ctrip.com/images/0106l1200086q9u7a57FA_W_640_10000.jpg?proc=autoorient"
    ]
}