{
    "counts": 10,
    "reviews": [
        {
            "id": 0,
            "name": "M30****5416",
            "user_id": "user_1274",
            "content": "一行四人从浙江过来桂林旅游。乘座万程号游船，船仓环境很好。看风景可去上面平台，一路景色很好。桂林山水甲天下。看了二十元人民币景色。九马画山。",
            "time": "2024-11-27",
            "score": 1.3,
            "score_count": 8,
            "visited_time": 827,
            "img_list": [
                "https://dimg04.c-ctrip.com/images/1mh3612000gwjd2wk6EB4_W_640_10000.jpg?proc=autoorient",
                "images/0_1.jpg",
                "images/0_2.jpg",
                "images/0_3.jpg",
                "https://dimg04.c-ctrip.com/images/1mh6812000gwj8m2g3042_W_640_10000.jpg?proc=autoorient",
                "https://dimg04.c-ctrip.com/images/1mh1b12000gwhrd8e8CBC_W_640_10000.jpg?proc=autoorient",
                "images/0_6.jpg",
                "https://dimg04.c-ctrip.com/images/1mh6i12000gwihkre9E9E_W_640_10000.jpg?proc=autoorient"
            ]
        },
        {
            "id": 1,
            "name": "不太空的一棵树",
            "user_id": "user_1285",
            "content": "漓江游船的航线主要是从桂林磨盘山码头或竹江码头到阳朔段，这段航线被认为是漓江航区的精华部分。游客可以在这里欣赏到漓江的奇山秀水、飘渺的烟雾和清丽的倒影，仿佛置身于仙境。游览时长大约为4.5小时，沿途可以观赏到冠岩、童子拜观音、九马画山、黄布倒影等著名景点。\n购买游船票需要提前预定，尤其是在旺季，票源非常紧张。\n游船上的座位宽敞舒适，环境干净。座位是提前预定好的，也可以上到楼顶的甲板看风景。\n碰到雨天，漓江的风景更加迷人，云雾缭绕的山峰呈现出别样的美感。\n到达阳朔码头后，游客需要走较长的路程才能出码头，沿途有摊贩售卖商品。",
            "time": "2024-11-22",
            "score": 3.4,
            "score_count": 10,
            "visited_time": 303,
            "img_list": [
                "images/1_0.jpg",
                "images/1_1.jpg",
                "images/1_2.jpg",
                "images/1_3.jpg"
            ]
        },
        {
            "id": 2,
            "name": "山羊脚",
            "user_id": "user_1296",
            "content": "选择四星船，还是不错的选择，适合老年人，楼下是下舱，二楼是一等座，二楼靠船头是VIP，位子更好一点。工作人员介绍就在眼前、更亲切一点，不然就是听声音。餐标无论哪里一个级别都是一样的。甲板也是都可以自由上去的，有二和三楼。很多带行李箱的，借水路从桂林到阳朔，挺好的。又有风景看。当中美女还会表演古筝，包含一顿自助餐。这个就普通。反正该有的都有了。人多，就基本取一轮就收摊了，反正也不是以吃为主。沿途风景反正就是你自己看看也可以，地标都会广播，然后人就比较多。整体还是挺专业的，服务。带老人小孩是个省心的选择。",
            "time": "2021-01-09",
            "score": 1.3,
            "score_count": 9,
            "visited_time": 573,
            "img_list": [
                "images/2_0.jpg",
                "images/2_1.jpg",
                "images/2_2.jpg",
                "images/2_3.jpg",
                "images/2_4.jpg",
                "https://dimg04.c-ctrip.com/images/03059120008djf00k3C20_W_640_10000.jpg?proc=autoorient",
                "https://dimg04.c-ctrip.com/images/03060120008djc3ac4AAD_W_640_10000.jpg?proc=autoorient",
                "images/2_7.jpg",
                "images/2_8.jpg"
            ]
        },
        {
            "id": 3,
            "name": "M26****8987",
            "user_id": "user_1396",
            "content": "找到旅行社订的漓江四星游船VIP舱的票，票价430，坐的银河189号游船。上船之后发现vip 舱和上舱没什么差别，某些方面还不如上舱，主要就是位置在二层船头且讲解员站在船头这里讲解，其他的座位和上舱一样，都是16个座位，并且最让我不爽的一点就是，自助餐的位置在上舱那边，游船工作人员一说开饭，等到我们去乘菜时，有几种都被抢空了，算了，简单地吃点吧。\n说是自助餐，其实也就那样总共也就十来种菜，而且都是凉的，有米饭、红薯、河粉、鱼块、油炸翅根、饼干、薯条、汤等等。熱菜嘛，有是有的，上船之后，工作人员会强烈推荐套餐啦、特色菜啦、小吃啦。扫了眼价格最便宜的80，其他的100、300、500的都是，船上4小时有些无聊，点了一份小食，100块，有5样，小碟子装的，一份田螺，其他四样都油炸：小螃蟹、小鱼、小河虾，还有个像是芋头，没吃出来，并送份西瓜；西瓜的卖相明显比自助餐的西瓜的卖相好。小食味道还行，但有些戳嘴。\n沿岸的风景优美壮观，漓江水清澈见底，两岸时不时能看到牛、鸭子，鸟等动物，发挥自己的想象，两岸的各种山头就是一幅幅美景。\n在龙头山码头下的船，一路上看到各种举牌拉人的，都15元/人，感觉不是正规的，也比较乱，联系旅行社，说是沿着长廊走到出口处有正规的观光车售票，结果：呵呵，还是15元/人，而且就不是像车站一样排队上车，就一窝蜂的乱挤，没一点秩序，谁最能见缝插针，最能抢，上车最快。\n本身游船还是挺满意的，座位舒适，风景好，但是就出码头的这一段路，好心情毁了大半。1、乘车乱，没人疏通；2、厕所脏乱差，没人打扫，每个坑里都堆满了屎；3、景区里没什么秩序，全是挤啊，抢啊，很闹心。",
            "time": "2019-10-05",
            "score": 2.7,
            "score_count": 9,
            "visited_time": 900,
            "img_list": [
                "images/3_0.jpg",
                "images/3_1.jpg",
                "images/3_2.jpg",
                "images/3_3.jpg",
                "images/3_4.jpg",
                "https://dimg04.c-ctrip.com/images//100f190000015r46sEE77_W_640_10000.jpg?proc=autoorient",
                "images/3_6.jpg",
                "images/3_7.jpg",
                "images/3_8.jpg",
                "images/3_9.jpg",
                "https://dimg04.c-ctrip.com/images//100u190000015r2ggE9CD_W_640_10000.jpg?proc=autoorient"
            ]
        },
        {
            "id": 4,
            "name": "ann****0my",
            "user_id": "user_1442",
            "content": "从携程订票之后立刻有人电话联系，并发短信通知取票方式。整体取票流程还是挺顺畅。邮轮9点开始登船，9:30开船，整个行程约4.5小时，途中经过景点如图3。\n邮轮上有收费的摄影服务，130块钱10张照片，多一张加10元，性价比还可以。主要是为了拍照方便，不然一堆人挤来挤去怎么也照不好。\n船上硬件条件不错，但是服务不太行。有人在船舱大声喧哗或者小朋友乱跑乱叫，服务员不会维持秩序，只热衷于推销午饭套餐。二楼洗手间没有水。午餐自助要排队取餐，菜品种类有限。可以多次取餐但是一个人只发一个盘子，盘子脏了没得换。\n不要订VIP，途经经典的时候大家都会跑到vip舱拍照（因为vip舱在二层船头。一点也没有vip的感觉。\n整体行程还是满意的，从桂林到阳朔的最佳路线就是坐游轮，舒适，且不会错过漓江各个景点。",
            "time": "2023-01-19",
            "score": 3.7,
            "score_count": 5,
            "visited_time": 745,
            "img_list": [
                "images/4_0.jpg",
                "https://dimg04.c-ctrip.com/images/0EQ3b12000agxhmi5881C_W_640_10000.jpg?proc=autoorient",
                "images/4_2.jpg",
                "images/4_3.jpg",
                "https://dimg04.c-ctrip.com/images/0EQ3c12000agxfti224D6_W_640_10000.jpg?proc=autoorient",
                "images/4_5.jpg"
            ]
        },
        {
            "id": 5,
            "name": "匿名用户",
            "user_id": "user_1486",
            "content": "绝对推荐，游玩桂林阳朔，必须乘坐游船才能真正体验到漓江甲天下的美丽风景。我们乘坐四星邮轮，从竹江码头上船到阳朔，全程共计60多公里，4.5小时，经过20多个主要景点。十一期间，天气非常好，随手一拍就是风景画。服务人员太度非常好，船上有导游一路讲解到位；船上提供免费自助餐。全部经过桂林阳朔的主要美景，可以说只要你乘坐游船基本把阳朔的美景游览完了。",
            "time": "2024-10-18",
            "score": 1.5,
            "score_count": 7,
            "visited_time": 722,
            "img_list": [
                "images/5_0.jpg",
                "https://dimg04.c-ctrip.com/images/0EQ0n12000g6w0kjmF58A_W_640_10000.jpg?proc=autoorient",
                "https://dimg04.c-ctrip.com/images/0EQ1z12000g6wl4ms68C4_W_640_10000.jpg?proc=autoorient",
                "https://dimg04.c-ctrip.com/images/0EQ3r12000g6ws1dh36B0_W_640_10000.jpg?proc=autoorient",
                "images/5_4.jpg",
                "images/5_5.jpg",
                "images/5_6.jpg",
                "images/5_7.jpg",
                "images/5_8.jpg"
            ]
        },
        {
            "id": 6,
            "name": "fbi489",
            "user_id": "user_1536",
            "content": "选的四星船上仓，整体行驶的很平稳。本来选的盛景号临时没开船给换的万程号。硬件设施还凑活，但感觉有些偏旧了，沙发靠背角度有点直，不算很舒服。一路景色倒是很美，基本上都在舱外看风景。午餐一般，盒饭水平。没在船上点餐，船上的饮料卖的太贵了，一听可乐要20，最好上船前买好饮料。",
            "time": "2024-10-10",
            "score": 1.0,
            "score_count": 10,
            "visited_time": 384,
            "img_list": [
                "https://dimg04.c-ctrip.com/images/0EQ5d12000g2qafgq4449_W_640_10000.jpg?proc=autoorient",
                "https://dimg04.c-ctrip.com/images/0EQ4712000g2qe1wd1326_W_640_10000.jpg?proc=autoorient",
                "images/6_2.jpg",
                "images/6_3.jpg",
                "images/6_4.jpg",
                "https://dimg04.c-ctrip.com/images/0EQ5612000g2q8vp3F252_W_640_10000.jpg?proc=autoorient",
                "https://dimg04.c-ctrip.com/images/0EQ4c12000g2q8cih4045_W_640_10000.jpg?proc=autoorient",
                "images/6_7.jpg",
                "https://dimg04.c-ctrip.com/images/0EQ3i12000g2pvijrEB67_W_640_10000.jpg?proc=autoorient"
            ]
        },
        {
            "id": 7,
            "name": "太那啥了吧",
            "user_id": "user_1593",
            "content": "一直以来对于旅游区的各种观光船游艇快艇摩托艇都是持排斥态度，但这一次直到上船才发现好悬哦，与一次几近完美的旅程差点就擦肩而过哈……由于带着七十多岁的老爸老妈出行，最初根本就没考虑坐船，而且已经在*州租了车子准备第二天自驾去阳朔，对于游船满大街都在招揽生意以为又是旅游区惯常的揽客骗钱的套路，后来发现了这个携程的这个四星游船预定的介绍才动了心，做了充分功课后付款预定，延期了当日的租车订单，不过下定后仍然心里惴惴不安，怕老人家受苦，浪费时间金钱不说，吃不好休息不好啥啥的……第二天等了船才发现船上设施完备，整洁干净，两层客舱都是只有十几个座位，绝对的高舒适度体验，服务人员彬彬有礼，中午的自助餐干净卫生吃的饱，沿途的风光就更是觉得值回票价了，那么美的漓江山水可以随意拍放心拍，和自驾、徒步、竹筏等等比起来简直就是完胜，老爸老妈感慨这次漓江游船是这次广西之行最美好的体验，三个半小时的路程一路开心拍照，欣赏风景，觉得过得很快！呵呵，差点错过的漓江游船之旅。",
            "time": "2023-05-06",
            "score": 4.3,
            "score_count": 6,
            "visited_time": 384,
            "img_list": [
                "https://dimg04.c-ctrip.com/images/0EQ6z12000b5yai881BA4_W_640_10000.jpg?proc=autoorient",
                "https://dimg04.c-ctrip.com/images/0EQ3612000b5y9z4966BC_W_640_10000.jpg?proc=autoorient",
                "https://dimg04.c-ctrip.com/images/0EQ4a12000b5xlovb2868_W_640_10000.jpg?proc=autoorient",
                "https://dimg04.c-ctrip.com/images/0EQ6o12000b5xzr1i5761_W_640_10000.jpg?proc=autoorient",
                "https://dimg04.c-ctrip.com/images/0EQ6z12000b5ycm8k82CC_W_640_10000.jpg?proc=autoorient",
                "https://dimg04.c-ctrip.com/images/0EQ3i12000b5y1vhg89BD_W_640_10000.jpg?proc=autoorient",
                "images/7_6.jpg",
                "https://dimg04.c-ctrip.com/images/0EQ0512000b5y5wm0B19D_W_640_10000.jpg?proc=autoorient",
                "https://dimg04.c-ctrip.com/images/0EQ5712000b5xwwgpB294_W_640_10000.jpg?proc=autoorient"
            ]
        },
        {
            "id": 8,
            "name": "BON970",
            "user_id": "user_1639",
            "content": "四星级游船 硬件不错\n软件太差强人意 \n上船开始推销午餐套餐 分260和400二种\n紧接着摄影套餐推销\n摄影师招揽生意可以理解\n但\n整个游船过程 甲板上\n充斥摄影师的麦克风扰民声\n严重影响整个旅游体验感\n\n对桂林旅游局推出的桂林名片漓江游\n失望至极 \n体验感大打折扣\n\n行程最后\n服务人员再次推销香水套餐\n\n直观感受就是商务舱+春秋客舱营销商品的结合体",
            "time": "2022-10-22",
            "score": 2.9,
            "score_count": 7,
            "visited_time": 956,
            "img_list": [
                "images/8_0.jpg",
                "https://dimg04.c-ctrip.com/images/0302f12000a3eaut107FA_W_640_10000.jpg?proc=autoorient",
                "https://dimg04.c-ctrip.com/images/0300b12000a3e8pcz2A3C_W_640_10000.jpg?proc=autoorient",
                "https://dimg04.c-ctrip.com/images/0300912000a3e8rqk589A_W_640_10000.jpg?proc=autoorient",
                "images/8_4.jpg"
            ]
        },
        {
            "id": 9,
            "name": "201****891",
            "user_id": "user_1664",
            "content": "乘坐游船游漓江是个不错的选择。漓江比较长，路上游览各个景点不如水上走方便。夏天天热又晒，坐在船里有空调，比较舒服。遇到景点，船上会广播通知乘客，乘客可以登梯到顶上的平台拍照，视野很开阔，行程时间安排也紧凑。一个个江畔的景点，通过游船半天的时间就全看到了，很不错。游船一早从竹江码头出发，人不是很多，行程不紧不慢，中午午后到阳朔，很舒服。",
            "time": "2021-07-05",
            "score": 1.7,
            "score_count": 8,
            "visited_time": 931,
            "img_list": [
                "https://dimg04.c-ctrip.com/images/01053120008s5a3toC54D_W_640_10000.jpg?proc=autoorient",
                "https://dimg04.c-ctrip.com/images/01006120008s5ci1t2262_W_640_10000.jpg?proc=autoorient",
                "https://dimg04.c-ctrip.com/images/0101m120008s5ca6cC0B7_W_640_10000.jpg?proc=autoorient",
                "https://dimg04.c-ctrip.com/images/01061120008s5e65o029B_W_640_10000.jpg?proc=autoorient",
                "images/9_4.jpg",
                "images/9_5.jpg",
                "https://dimg04.c-ctrip.com/images/01032120008s5d1a84AA3_W_640_10000.jpg?proc=autoorient",
                "https://dimg04.c-ctrip.com/images/0106h120008s5ebwuDEB7_W_640_10000.jpg?proc=autoorient",
                "https://dimg04.c-ctrip.com/images/0101j120008s5bqq472A1_W_640_10000.jpg?proc=autoorient"
            ]
        }
    ],
    "spot_id": 148
}