{
    "id": 4,
    "name": "瑞克在远方",
    "user_id": "user_2422",
    "content": "历史文化底蕴深厚\n\n• 明水古城始建于唐朝，历经千年沧桑，见证了诸多王朝的兴衰更迭，是章丘四大名镇之一，曾是商贾云集、文化繁荣的商贸中心.\n\n• 古城内有李清照故居、孟家大院等历史古迹，还能看到宗祠建筑以及祭祖、庙会等代代相传的古老传统，承载着深厚的文化底蕴.\n\n自然景观优美\n\n• 这里有“小泉城”美誉，景区包含百脉泉泉系， 墨泉、梅花泉等各有特色，泉水清澈凉爽，与古城建筑相得益彰，构成一幅天然的水墨画卷.\n\n• 古城外的莲藕池，莲叶田田，莲花争艳，城内小巷古树参天，青藤绿植爬满墙壁，充满田园风光，让人心旷神怡.\n\n建筑风格独特\n\n• 以明清建筑为主，白墙灰瓦，飞檐翘角，尽显传统韵味，城墙气势恢宏，城楼威严壮观，雕饰精美，古街古巷纵横交错，漫步其中仿佛穿越回古代.\n\n游玩体验丰富\n\n• 既有手工艺展示区、传统美食体验区等特色区域，又有戏曲表演、民俗展示等文化活动，还引入了虚拟现实等现代科技元素，游客可感受古老文化与现代文明的交融\n\n• 可以乘船游览，欣赏沿途的护城河、内河及各种桥梁，感受江南水乡般的韵味.\n\n• 夜幕降临后，有超美的无人机表演，华灯亮起，复古建筑非常适合拍照，此外还有全天多达八十场的演出，如宋乐清词、包公案等.\n\n配套设施较完善\n\n• 周边停车场多，停车方便可满足基本的住宿和吃需求.",
    "time": "2024-12-05",
    "score": 1.2,
    "score_count": 10,
    "visited_time": 889,
    "img_list": [
        "images/4_0.jpg"
    ]
}