{
    "id": 8,
    "name": "偶尔装一下",
    "user_id": "user_1131",
    "content": "今天我以一个退役军人的身份，薅了国家两次羊毛。游玩杜甫草堂和金沙遗址博物馆均凭军人优待证免费入园，省多少门票钱不重要，身份感暴棚了身份证的价值取向，有几分光荣，些许得瑟，一小撮优越感，坐享了多半天特权主义。出馆后，不考虑坐公交车地铁了，一伸手打个车，结果免单的门票钱全给出租车司机交油钱了。我就是这样经常干一些捡芝麻丢西瓜的事。完了还不忘用阿Q精神开导自己，想开点，上年纪了，钱不花是纸，花了才是钱，钱💰是身上的垢夹搓了还有，故，应当及时行乐来调侃一下自己。\n        进了杜甫草堂，这才想起来，对于我收获的小确幸，应该吟[嘴唇]几句李白的《将进酒》[啤酒]来表达一下我沉醉优待的心情， 人生得意须尽欢，莫使金樽空对月，千金散尽还复来，方显应景。\n杜甫草堂，除了自然景观，园林绿化，几乎全是复建，复修，复仿的建筑，但能看的出来全是史料中记载中的文献铺垫出的真实还原。每一处都有着正史的佐证以及几代文人笔耕不缀的努力和探索，为杜甫诗圣的遗风和文学贡献做着岁月的沉淀，留一份非物质文化遗产永享人间。景区的前世今生，杜甫的诗作.生平，百度，书籍均有，更全面更详细，我无需再费笔端，逐一着墨。\n       杜甫，字自美，号少陵野老，现实主义诗人，被世人尊为诗圣。杜甫草堂的栖息地，是他人生暂时路过偏安一隅的地方，尽管经历了野无遗贤，终不得志的一生，但在兵荒马乱颠沛流离时选择安居乐业的草堂和他笔端下的诗一样，画意，情意，安逸，飘逸，俊逸，惬意，意义具全。\n       忘记杜甫草堂的名字，我以为我置身于一所寺庙，清心寡欲，淡泊无为。我们家老太太出景区时，一本正经的问我，这座寺庙怎么没人上香，也看不见僧人。我逗她说，全开会去了。她还来了一个，噢。看他煞有介事的问答，直接让我笑不活了。\n       草堂里的青竹林，错落有致，腰身挺拔，俊朗洒脱，一副君子相。给老太太拍照时，我对她说，虽然你没上过一天学，大字不识几个，但此刻，你是长安.竹林妻闲，从今天开始也是个文化人儿，老太太兴奋的跟刚大学毕业似的。虽然她不知道竹林七贤原来都混哪里，姓甚名谁。我也不知道，管他呢，眼下的老娘，老小老小，咋高兴咋哄着来。\n       其实，我想表达的是，尽管杜甫草堂不是上香礼佛之处，初涉此地，宁静致远，心静如水的感受不自觉的由然而生，我想，这是杜甫的人格魅力。",
    "time": "2024-06-30",
    "score": 1.9,
    "score_count": 4,
    "visited_time": 747,
    "img_list": [
        "images/8_0.jpg",
        "images/8_1.jpg",
        "images/8_2.jpg"
    ]
}