{
    "id": 4,
    "name": "可爱宝贝苗苗的爸爸",
    "user_id": "user_244",
    "content": "拙政园的园林景观十分优美，特别是其独特的园林造景艺术手法更是引人入胜。虽然距离市中心不远，但建议自驾前往，将车辆停在附近的停车场后步行到达。园区内的步道宽敞且整洁，非常适合悠闲地漫步。 \n在.拙政园，可以看到各种精美的古建筑和别致的庭院设计，如小飞虹、远香堂、香洲以及玉兰堂等。这些景点不仅展示了古代工匠的高超技艺， 还体现了文人雅士的生活情趣。此外，拙政园还是一处观赏荷花的好地方，尤其是在夏季，荷花盛开，美不胜收。 \n拙政园作为世界文化遗产，具有极高的历史文化价值。无论是独自一人前来欣赏美景，还是带着家人一起度过愉快的时光，这里都能满足你的需求。同时，由于目前处于淡季，门票价格较为亲民，对老年人和学生群体也提供了优惠政策，非常划算。",
    "time": "2025-01-08",
    "score": 3.6,
    "score_count": 4,
    "visited_time": 353,
    "img_list": [
        "images/4_0.jpg",
        "images/4_1.jpg",
        "images/4_2.jpg",
        "images/4_3.jpg",
        "images/4_4.jpg",
        "images/4_5.jpg",
        "images/4_6.jpg",
        "images/4_7.jpg",
        "images/4_8.jpg",
        "images/4_9.jpg",
        "images/4_10.jpg",
        "images/4_11.jpg",
        "images/4_12.jpg",
        "images/4_13.jpg",
        "images/4_14.jpg"
    ]
}